finvizscrapper/__init__.py
finvizscrapper/finviz_screener.py
finvizscrapper-0.0.3.dist-info/METADATA
finvizscrapper-0.0.3.dist-info/WHEEL
finvizscrapper-0.0.3.dist-info/top_level.txt
finvizscrapper-0.0.3.dist-info/RECORD
